threaded_multihost/__init__.py
threaded_multihost/fields.py
threaded_multihost/middleware.py
threaded_multihost/multihost_patch.py
threaded_multihost/sites.py
threaded_multihost/threadlocal_settings.py
threaded_multihost/threadlocals.py
threaded_multihost/utils.py
djangoplicity_threaded_multihost-1.4.post2.dist-info/LICENSE.rst
djangoplicity_threaded_multihost-1.4.post2.dist-info/METADATA
djangoplicity_threaded_multihost-1.4.post2.dist-info/WHEEL
djangoplicity_threaded_multihost-1.4.post2.dist-info/top_level.txt
djangoplicity_threaded_multihost-1.4.post2.dist-info/RECORD
