Metadata-Version: 2.1
Name: djangoplicity-threaded-multihost
Version: 1.4-2
Summary: Djangoplicity Threaded Multihost
Home-page: https://github.com/djangoplicity/djangoplicity-threaded-multihost
Author: Bruce Kroeze
Author-email: brucek@solidsitesolutions.com
License: New BSD License
Download-URL: https://github.com/djangoplicity/djangoplicity-threaded-multihost/archive/refs/tags/1.4.2.tar.gz
Platform: any
Classifier: Development Status :: 4 - Beta
Classifier: Environment :: Web Environment
Classifier: Intended Audience :: Developers
Classifier: License :: OSI Approved :: BSD License
Classifier: Operating System :: OS Independent
Classifier: Programming Language :: Python
Classifier: Framework :: Django
License-File: LICENSE.rst
